validator_regex/RegexValidator.py
validator_regex/ValidatorContext.py
validator_regex/__init__.py
validator_regex/strategies/BRLCurrencyValidation.py
validator_regex/strategies/CNPJValidation.py
validator_regex/strategies/CPFValidation.py
validator_regex/strategies/EmailValidation.py
validator_regex/strategies/NameValidation.py
validator_regex/strategies/TimeValidation.py
validator_regex/strategies/ValidationStrategy.py
validator_regex-0.1.0.dist-info/METADATA
validator_regex-0.1.0.dist-info/WHEEL
validator_regex-0.1.0.dist-info/licenses/LICENSE
validator_regex-0.1.0.dist-info/RECORD
