Metadata-Version: 2.4
Name: validator-regex
Version: 0.1.0
Summary: Validador de entradas com expressões regulares (Regex) em Python, usando o padrão Strategy. Suporte a e-mails, valores monetários, CPF, CNPJ, hora e nomes.
License-File: LICENSE
Keywords: regex,validator,strategy,python,pypi,validation
Author: jcarlossc
Author-email: jcarlossc1977@gmail.com
Requires-Python: >=3.13
Classifier: Development Status :: 3 - Alpha
Classifier: Intended Audience :: Developers
Classifier: License :: OSI Approved :: MIT License
Classifier: Operating System :: OS Independent
Classifier: Programming Language :: Python :: 3
Classifier: Programming Language :: Python :: 3.13
Classifier: Programming Language :: Python :: 3.14
Classifier: Topic :: Software Development :: Libraries
Requires-Dist: regex (>=2025.10.23,<2026.0.0)
